{
    "$schema": "http://json-schema.org/draft-07/schema#",
    "type": "object",
    "properties": {
        "Component": {
            "const": "RawMaterialGenerator"
        },
        "Properties": {
            "type": "array",
            "items": {
                "type": "object",
                "properties": {
                    "Key": {
                        "enum": [
                            "SpeedMultiplier"
                        ]
                    }
                },
                "allOf": [
                    {
                        "if": {
                            "properties": {
                                "Key": {
                                    "const": "SpeedMultiplier"
                                }
                            }
                        },
                        "then": {
                            "$ref": "../types.schema.json#/definitions/Float"
                        }
                    }
                ]
            }
        }
    },
    "required": ["Component", "Properties"]
}